{
  "_id": "2fK608aSYU9QDmzw",
  "name": "Heavy Steel Shield",
  "type": "equipment",
  "img": "systems/pf1/icons/items/armor/shield-heavy-metal.png",
  "system": {
    "description": {
      "value": "<p>You strap a heavy steel shield to your forearm and grip it with your hand. A heavy steel shield is so heavy that you can’t use your shield hand for anything else. Whether wooden or steel, a heavy shield offers the same basic protection and attack benefits, though the two versions respond differently to some spells and effects (such as rusting grasp). A druid can use a heavy wooden shield, but not a heavy steel shield.</p>"
    },
    "weight": {
      "value": 15
    },
    "price": 20,
    "hp": {
      "max": 20,
      "value": 20
    },
    "hardness": 10,
    "subType": "shield",
    "equipmentSubtype": "heavyShield",
    "armor": {
      "value": 2,
      "acp": 2
    },
    "spellFailure": 15,
    "slot": "shield"
  }
}
