{
  "_id": "YCrz2YNXSylt4Gl3",
  "name": "Madsen Light Machine Gun",
  "type": "weapon",
  "img": "icons/weapons/guns/rifle-brown.webp",
  "data": {
    "description": {
      "value": "<p><strong>Source</strong> <em>Pathfinder #71: Rasputin Must Die! pg. 64</em></p>\n<h3 class=\"framing\">Statistics</h3>\n<p><strong>Cost</strong> 1,000 gp <strong>Weight</strong> 20 lbs.</p>\n<p><strong>Damage</strong> 2d6 (medium); <strong>Critical</strong> x4; <strong>Range</strong> 100 ft.; <strong>Type</strong> B and P; <strong>Special</strong> automatic</p>\n<p><strong>Misfire</strong> 1-2; <strong>Capacity</strong> 20, 30, or 40</p>\n<p><strong>Category</strong> Two-Handed; <strong>Proficiency</strong> Exotic</p>\n<h3 class=\"framing\">Description</h3>\n<p>This imposing machine gun is light enough to be transported and wielded by a single user. Chambered for the Russian military in 7.62 54mmR, this machine gun uses a top-loading, detachable 20-, 30-, or 40-round magazine.</p>\n<p>Like most machine guns, it is only capable of automatic fire.</p>",
      "chat": "",
      "unidentified": ""
    },
    "tags": [],
    "quantity": 1,
    "weight": 20,
    "price": 1000,
    "size": "med",
    "equipped": true,
    "resizing": false,
    "identified": true,
    "hp": {
      "max": "10",
      "value": "10"
    },
    "broken": false,
    "hardness": 10,
    "carried": true,
    "unidentified": {
      "price": 0,
      "name": ""
    },
    "identifiedName": "Madsen Light Machine Gun",
    "cl": 0,
    "aura": {
      "custom": false,
      "school": ""
    },
    "changes": [],
    "changeFlags": {
      "loseDexToAC": false,
      "noEncumbrance": false,
      "mediumArmorFullSpeed": false,
      "heavyArmorFullSpeed": false
    },
    "activation": {
      "cost": 1,
      "type": "attack"
    },
    "unchainedAction": {
      "activation": {
        "cost": 1,
        "type": ""
      }
    },
    "duration": {
      "value": null,
      "units": "inst"
    },
    "target": {
      "value": ""
    },
    "range": {
      "value": "100",
      "units": "ft",
      "maxIncrements": 10,
      "minValue": null,
      "minUnits": ""
    },
    "uses": {
      "value": 0,
      "per": "",
      "autoDeductCharges": true,
      "autoDeductChargesCost": "1",
      "maxFormula": ""
    },
    "measureTemplate": {
      "type": "",
      "size": "",
      "overrideColor": false,
      "customColor": "",
      "overrideTexture": false,
      "customTexture": ""
    },
    "attackName": "",
    "actionType": "rwak",
    "attackBonus": "",
    "critConfirmBonus": "",
    "damage": {
      "parts": [
        [
          "sizeRoll(2, 6, @size)",
          "B and P"
        ]
      ],
      "critParts": [],
      "nonCritParts": []
    },
    "attackParts": [],
    "formulaicAttacks": {
      "count": {
        "formula": "ceil(@attributes.bab.total / 5) - 1"
      },
      "bonus": {
        "formula": "@formulaicAttack * -5"
      },
      "label": ""
    },
    "formula": "",
    "ability": {
      "attack": "dex",
      "damage": "",
      "damageMult": 1.5,
      "critRange": 20,
      "critMult": 4
    },
    "save": {
      "dc": "0",
      "type": "",
      "description": ""
    },
    "effectNotes": [],
    "attackNotes": [],
    "soundEffect": "",
    "contextNotes": [],
    "links": {
      "children": []
    },
    "tag": "madsenLightMachineGun",
    "useCustomTag": false,
    "flags": {
      "boolean": [],
      "dictionary": []
    },
    "scriptCalls": [],
    "masterwork": false,
    "enh": null,
    "attackType": "weapon",
    "nonlethal": false,
    "proficient": true,
    "primaryAttack": true,
    "held": "2h",
    "weaponType": "exotic",
    "weaponSubtype": "2h",
    "properties": {
      "blc": false,
      "brc": false,
      "dea": false,
      "dis": false,
      "dst": false,
      "dbl": false,
      "fin": false,
      "frg": false,
      "grp": false,
      "imp": false,
      "mnk": false,
      "nnl": false,
      "prf": false,
      "rch": false,
      "snd": false,
      "thr": false,
      "trp": false
    },
    "showInQuickbar": true,
    "conditionals": [],
    "spellArea": ""
  },
  "effects": [],
  "folder": null,
  "sort": 0,
  "permission": {
    "default": 0
  },
  "flags": {}
}