{
  "_id": "EnMgClQRxY1GXg4e",
  "name": "Awesome Blow",
  "type": "feat",
  "img": "systems/pf1/icons/skills/violet_28.jpg",
  "sort": 0,
  "flags": {},
  "system": {
    "description": {
      "value": "<p>At 16th level, the brawler can as a standard action perform an awesome blow combat maneuver against a corporeal creature of her size or smaller. If the combat maneuver check succeeds, the opponent takes damage as if the brawler hit it with the close weapon she is wielding or an unarmed strike, it is knocked flying 10 feet in a direction of the brawler’s choice, and it falls prone. The brawler can only push the opponent in a straight line, and the opponent can’t move closer to the brawler than the square it started in. If an obstacle prevents the completion of the opponent’s move, the opponent and the obstacle each take 1d6 points of damage, and the opponent is knocked prone in the space adjacent to the obstacle. (Unlike the <a href=\"https://www.aonprd.com/FeatDisplay.aspx?ItemName=Awesome%20Blow\">Awesome Blow</a> monster feat, the brawler can be of any size to use this ability.)</p>"
    },
    "tags": [],
    "actions": [
      {
        "_id": "6qxp6q3ielu2wa0c",
        "name": "Use",
        "img": "systems/pf1/icons/skills/violet_28.jpg",
        "description": "",
        "tag": "",
        "activation": {
          "cost": 1,
          "type": "standard"
        },
        "unchainedAction": {
          "activation": {
            "cost": 2,
            "type": "action"
          }
        },
        "duration": {
          "value": null,
          "units": ""
        },
        "target": {
          "value": ""
        },
        "range": {
          "value": null,
          "units": "",
          "maxIncrements": 1,
          "minValue": null,
          "minUnits": ""
        },
        "uses": {
          "autoDeductChargesCost": "",
          "self": {
            "value": 0,
            "maxFormula": "",
            "per": null
          },
          "per": "",
          "value": 0,
          "maxFormula": ""
        },
        "measureTemplate": {
          "type": "",
          "size": "",
          "overrideColor": false,
          "customColor": "",
          "overrideTexture": false,
          "customTexture": ""
        },
        "attackName": "",
        "actionType": "",
        "attackBonus": "",
        "critConfirmBonus": "",
        "damage": {
          "parts": [],
          "critParts": [],
          "nonCritParts": []
        },
        "attackParts": [],
        "formulaicAttacks": {
          "count": {
            "formula": ""
          },
          "bonus": {
            "formula": ""
          },
          "label": null
        },
        "formula": "",
        "ability": {
          "attack": null,
          "damage": null,
          "damageMult": 1,
          "critRange": 20,
          "critMult": 2
        },
        "save": {
          "dc": 0,
          "type": "",
          "description": ""
        },
        "effectNotes": [],
        "attackNotes": [],
        "soundEffect": "",
        "powerAttack": {
          "multiplier": "",
          "damageBonus": 2,
          "critMultiplier": 1
        },
        "naturalAttack": {
          "primaryAttack": true,
          "secondary": {
            "attackBonus": "-5",
            "damageMult": 0.5
          }
        },
        "nonlethal": false,
        "usesAmmo": false,
        "spellEffect": "",
        "spellArea": "",
        "conditionals": [],
        "enh": {
          "value": null
        }
      }
    ],
    "uses": {
      "per": ""
    },
    "attackNotes": [],
    "effectNotes": [],
    "changes": [],
    "contextNotes": [],
    "links": {
      "children": [],
      "charges": []
    },
    "tag": "classFeat_awesomeBlow",
    "useCustomTag": true,
    "armorProf": {
      "value": []
    },
    "weaponProf": {
      "value": []
    },
    "languages": {
      "value": []
    },
    "scriptCalls": [],
    "subType": "classFeat",
    "associations": {
      "classes": [["Brawler"]]
    },
    "abilityType": "ex"
  }
}
