{
  "_id": "K1mjj2mYEkZtIPJI",
  "name": "Immediate Change",
  "type": "feat",
  "img": "systems/pf1/icons/skills/light_07.jpg",
  "effects": [],
  "folder": null,
  "sort": 0,
  "flags": {},
  "system": {
    "description": {
      "value": "<p>The vigilante can change identities as a move action, and he no longer needs to spend extra time to adjust his appearance and persona.</p>\n<p>A vigilante must be at least 13th level and must have the quick change social talent to select this talent.</p>"
    },
    "tags": [],
    "actions": [],
    "attackNotes": [],
    "effectNotes": [],
    "changes": [],
    "contextNotes": [],
    "links": {
      "children": [],
      "charges": []
    },
    "tag": "classFeat_immediateChange",
    "useCustomTag": true,
    "armorProf": {
      "value": []
    },
    "weaponProf": {
      "value": []
    },
    "languages": {
      "value": []
    },
    "scriptCalls": [],
    "featType": "classFeat",
    "associations": {
      "classes": [["Vigilante"]]
    },
    "abilityType": "ex"
  },
  "ownership": {
    "default": 0
  },
  "_stats": {
    "systemId": "pf1",
    "systemVersion": "0.81.3",
    "coreVersion": "10.277",
    "createdTime": null,
    "modifiedTime": 1659670360145,
    "lastModifiedBy": "PoIR9pEzkZzq4MMu"
  },
  "permission": {
    "default": 0
  }
}
