{
  "_id": "QzNDIUZajHu8pdxg",
  "name": "Smoke Subdomain",
  "type": "feat",
  "img": "systems/pf1/icons/spells/fog-water-air-1.jpg",
  "sort": 0,
  "flags": {},
  "system": {
    "description": {
      "value": "<p><b>Replacement Domain Spells:</b></p>\n<ul>\n<li>2nd—@Compendium[pf1.spells.0d756xyqhinsstas]{Pyrotechnics}</li>\n<li>3rd—@Compendium[pf1.spells.kjke96zd1j1jz48z]{Stinking Cloud}</li>\n</ul>"
    },
    "tags": [],
    "actions": [],
    "attackNotes": [],
    "effectNotes": [],
    "changes": [],
    "contextNotes": [],
    "links": {
      "children": [],
      "charges": []
    },
    "tag": "classFeat_smokeSubdomain",
    "useCustomTag": true,
    "armorProf": {
      "value": []
    },
    "weaponProf": {
      "value": []
    },
    "languages": {
      "value": []
    },
    "scriptCalls": [],
    "subType": "classFeat",
    "associations": {
      "classes": [["Cleric"]]
    }
  }
}
