{
  "_id": "9zlmrafrgoPKjDZm",
  "name": "Kasatha",
  "type": "npc",
  "img": "systems/pf1/icons/races/human.jpg",
  "data": {
    "abilities": {
      "str": {
        "value": 13
      },
      "dex": {
        "value": 15
      },
      "con": {
        "value": 12
      },
      "wis": {
        "value": 14
      },
      "cha": {
        "value": 8
      }
    },
    "attributes": {
      "hp": {
        "value": 9
      },
      "spells": {
        "usedSpellbooks": []
      }
    },
    "details": {
      "alignment": "ln",
      "cr": {
        "base": 0.5
      }
    },
    "skills": {
      "acr": {
        "rank": 2
      },
      "clm": {
        "rank": 1
      },
      "esc": {
        "rank": 2
      },
      "sur": {
        "rank": -1
      }
    },
    "traits": {
      "senses": "Perception +3",
      "languages": {
        "value": [
          "common"
        ],
        "custom": "Kasatha"
      },
      "di": {
        "value": []
      },
      "dv": {
        "value": []
      },
      "ci": {
        "value": []
      },
      "stature": ""
    }
  },
  "token": {
    "name": "Kasatha",
    "displayName": 20,
    "actorLink": false,
    "width": 1,
    "height": 1,
    "scale": 1,
    "mirrorX": false,
    "mirrorY": false,
    "lockRotation": false,
    "rotation": 0,
    "alpha": 1,
    "vision": false,
    "dimSight": 0,
    "brightSight": 0,
    "dimLight": 0,
    "brightLight": 0,
    "sightAngle": 0,
    "lightAngle": 0,
    "lightAlpha": 0.25,
    "lightAnimation": {
      "speed": 5,
      "intensity": 5
    },
    "disposition": -1,
    "displayBars": 20,
    "bar1": {
      "attribute": null
    },
    "bar2": {
      "attribute": null
    },
    "flags": {
      "pf1": {
        "lowLightVision": false
      }
    },
    "randomImg": false,
    "img": "systems/pf1/icons/races/human.jpg"
  },
  "items": [
    {
      "_id": "VYbsatEW3DFCLWtD",
      "name": "Kasatha",
      "type": "race",
      "img": "systems/pf1/icons/races/orc.png",
      "data": {
        "description": {
          "value": "<h2>Standard Racial Traits</h2>\n<ul>\n<li><strong>Ability Score Modifiers:</strong> Kasathas are nimble and perceptive. They gain +2&nbsp;<a href=\"https://www.d20pfsrd.com/basics-ability-scores/ability-scores#TOC-Dexterity-Dex-\">Dexterity</a>&nbsp;and +2&nbsp;<a href=\"https://www.d20pfsrd.com/basics-ability-scores/ability-scores#TOC-Wisdom-Wis-\">Wisdom</a>)&nbsp;</li>\n<li><strong>Type:</strong>&nbsp;<a href=\"https://www.d20pfsrd.com/bestiary/rules-for-monsters/creature-types#TOC-Humanoid\">Humanoid</a>&nbsp;(kasatha)</li>\n<li><strong>Size:</strong> Kasathas are Medium creatures and have no bonuses or penalties due to their size.&nbsp;</li>\n<li><strong>Base Speed:</strong> Kasathas have a base speed of 30 feet.&nbsp;</li>\n<li><strong>Languages:</strong> Kasathas speak Common and Kasatha. A kasatha with a high&nbsp;<a href=\"https://www.d20pfsrd.com/basics-ability-scores/ability-scores#TOC-Intelligence-Int-\">Intelligence</a>&nbsp;score can choose from the following: Dwarven, Draconic,&nbsp;<a href=\"https://www.d20pfsrd.com/bestiary/monster-listings/humanoids/gnoll\">Gnoll</a>,&nbsp;<a href=\"https://www.d20pfsrd.com/races/other-races/featured-races/arg-orc\">Orc</a>, and&nbsp;<a href=\"https://www.d20pfsrd.com/bestiary/monster-listin/magical-beasts/sphinx\">Sphinx</a>.</li>\n<li><strong>Multi-Armed:</strong> A kasatha has four arms. One hand is considered its primary hand; all others are considered off hands. It can use any of its hands for other purposes that require free hands.&nbsp;</li>\n</ul>\n<h4>Defensive Abilities</h4>\n<ul>\n<li><strong>Defensive Training, Greater:</strong> Kasathas have a +2&nbsp;<a href=\"https://www.d20pfsrd.com/basics-ability-scores/glossary#TOC-Dodge-Bonus\">dodge bonus</a>&nbsp;to&nbsp;<a href=\"https://www.d20pfsrd.com/gamemastering/combat#TOC-Armor-Class\">Armor Class</a>.</li>\n<li><strong>Desert Runner: </strong>Kasathas have a +4&nbsp;<a href=\"https://www.d20pfsrd.com/basics-ability-scores/glossary#TOC-Racial-Bonus\">racial bonus</a>&nbsp;on&nbsp;<a href=\"https://www.d20pfsrd.com/basics-ability-scores/ability-scores#TOC-Constitution-Con-\">Constitution</a>&nbsp;checks and&nbsp;<a href=\"https://www.d20pfsrd.com/gamemastering/combat#TOC-Fortitude\">Fortitude</a>&nbsp;saves to avoid&nbsp;<a href=\"https://www.d20pfsrd.com/gamemastering/conditions#TOC-Fatigued\">fatigue</a>,&nbsp;<a href=\"https://www.d20pfsrd.com/gamemastering/conditions#TOC-Exhausted\">exhaustion</a>, and other ill effects from running, forced marches, starvation, thirst, and hot or cold environments.</li>\n</ul>\n<h4>Feat and Skill Abilities</h4>\n<ul>\n<li><strong>Stalker:</strong>&nbsp;<a href=\"https://www.d20pfsrd.com/skills/perception\">Perception</a>&nbsp;and&nbsp;<a href=\"https://www.d20pfsrd.com/skills/stealth\">Stealth</a>&nbsp;are class skills for kasathas.</li>\n<li><strong>Spinal Sword Proficiency:</strong> Kasathas treat kasatha spinal swords as martial weapons.</li>\n</ul>\n<p>Movement Abilities</p>\n<ul>\n<li><strong>Jumper:</strong> Kasathas are always considered to have a running start when attempting&nbsp;<a href=\"https://www.d20pfsrd.com/skills/acrobatics\">Acrobatics</a>&nbsp;checks to jump.</li>\n<li><strong>Desert Stride:</strong> Kasathas move through non-magical difficult terrain in desert environments at normal speed.</li>\n</ul>"
        },
        "tags": [],
        "changes": [
          {
            "_id": "ooq192v4",
            "formula": "2",
            "operator": "+",
            "subTarget": "dex",
            "modifier": "racial",
            "priority": 0,
            "value": 0,
            "target": "ability"
          },
          {
            "_id": "jewt36nh",
            "formula": "2",
            "operator": "+",
            "subTarget": "wis",
            "modifier": "racial",
            "priority": 0,
            "value": 0,
            "target": "ability"
          },
          {
            "_id": "7t85ovl0",
            "formula": "2",
            "operator": "+",
            "subTarget": "ac",
            "modifier": "dodge",
            "priority": 0,
            "value": 0,
            "target": "ac"
          }
        ],
        "contextNotes": [],
        "links": {
          "children": []
        },
        "armorProf": {
          "value": []
        },
        "weaponProf": {
          "value": []
        },
        "flags": {
          "boolean": [],
          "dictionary": []
        },
        "scriptCalls": [],
        "subTypes": [
          [
            "Kasatha"
          ]
        ]
      },
      "effects": [],
      "folder": null,
      "sort": 0,
      "permission": {
        "default": 0
      },
      "flags": {}
    },
    {
      "_id": "W8dxwZ1CZiwLKsqr",
      "name": "Monk",
      "type": "class",
      "img": "systems/pf1/icons/items/equipment/gloves.jpg",
      "data": {
        "description": {
          "value": "<p>For the truly exemplary, martial skill transcends the battlefield—it is a lifestyle, a doctrine, a state of mind. These warrior-artists search out methods of battle beyond swords and shields, finding weapons within themselves just as capable of crippling or killing as any blade. These monks (so called since they adhere to ancient philosophies and strict martial disciplines) elevate their bodies to become weapons of war, from battle-minded ascetics to self-taught brawlers. Monks tread the path of discipline, and those with the will to endure that path discover within themselves not what they are, but what they are meant to be.</p>\n<p><strong>Role</strong>: Monks excel at overcoming even the most daunting perils, striking where it’s least expected, and taking advantage of enemy vulnerabilities. Fleet of foot and skilled in combat, monks can navigate any battlefield with ease, aiding allies wherever they are needed most.</p>\n<p><strong>Alignment</strong>: Any lawful</p>\n<p><strong>Hit Die</strong>: d8</p>\n<p><strong>Starting Wealth</strong>: 1d6 × 10 gp (average 35 gp.) In addition, each character begins play with an outfit worth 10 gp or less.</p>\n<h2><span id=\"Class_Skills\">Class Skills</span></h2>\n<p>The monk’s class skills are&nbsp;<a href=\"https://www.d20pfsrd.com/skills/acrobatics\">Acrobatics</a>&nbsp;(<a href=\"https://www.d20pfsrd.com/basics-ability-scores/ability-scores#TOC-Dexterity-Dex-\">Dex</a>),&nbsp;<a href=\"https://www.d20pfsrd.com/skills/climb\">Climb</a>&nbsp;(<a href=\"https://www.d20pfsrd.com/basics-ability-scores/ability-scores#TOC-Strength-Str-\">Str</a>),&nbsp;<a href=\"https://www.d20pfsrd.com/skills/craft\">Craft</a>&nbsp;(<a href=\"https://www.d20pfsrd.com/basics-ability-scores/ability-scores#TOC-Intelligence-Int-\">Int</a>),&nbsp;<a href=\"https://www.d20pfsrd.com/skills/escape-artist\">Escape Artist</a>&nbsp;(<a href=\"https://www.d20pfsrd.com/basics-ability-scores/ability-scores#TOC-Dexterity-Dex-\">Dex</a>),&nbsp;<a href=\"https://www.d20pfsrd.com/skills/intimidate\">Intimidate</a>&nbsp;(<a href=\"https://www.d20pfsrd.com/basics-ability-scores/ability-scores#TOC-Charisma-Cha-\">Cha</a>),&nbsp;<a href=\"https://www.d20pfsrd.com/skills/knowledge\">Knowledge</a>&nbsp;(history) (<a href=\"https://www.d20pfsrd.com/basics-ability-scores/ability-scores#TOC-Intelligence-Int-\">Int</a>),&nbsp;<a href=\"https://www.d20pfsrd.com/skills/knowledge\">Knowledge</a>&nbsp;(religion) (<a href=\"https://www.d20pfsrd.com/basics-ability-scores/ability-scores#TOC-Intelligence-Int-\">Int</a>),&nbsp;<a href=\"https://www.d20pfsrd.com/skills/perception\">Perception</a>&nbsp;(<a href=\"https://www.d20pfsrd.com/basics-ability-scores/ability-scores#TOC-Wisdom-Wis-\">Wis</a>),&nbsp;<a href=\"https://www.d20pfsrd.com/skills/perform\">Perform</a>&nbsp;(<a href=\"https://www.d20pfsrd.com/basics-ability-scores/ability-scores#TOC-Charisma-Cha-\">Cha</a>),&nbsp;<a href=\"https://www.d20pfsrd.com/skills/profession\">Profession</a>&nbsp;(<a href=\"https://www.d20pfsrd.com/basics-ability-scores/ability-scores#TOC-Wisdom-Wis-\">Wis</a>),&nbsp;<a href=\"https://www.d20pfsrd.com/skills/ride\">Ride</a>&nbsp;(<a href=\"https://www.d20pfsrd.com/basics-ability-scores/ability-scores#TOC-Dexterity-Dex-\">Dex</a>),&nbsp;<a href=\"https://www.d20pfsrd.com/skills/sense-motive\">Sense Motive</a>&nbsp;(<a href=\"https://www.d20pfsrd.com/basics-ability-scores/ability-scores#TOC-Wisdom-Wis-\">Wis</a>),&nbsp;<a href=\"https://www.d20pfsrd.com/skills/stealth\">Stealth</a>&nbsp;(<a href=\"https://www.d20pfsrd.com/basics-ability-scores/ability-scores#TOC-Dexterity-Dex-\">Dex</a>), and&nbsp;<a href=\"https://www.d20pfsrd.com/skills/swim\">Swim</a>&nbsp;(<a href=\"https://www.d20pfsrd.com/basics-ability-scores/ability-scores#TOC-Strength-Str-\">Str</a>).</p>\n<p><strong>Skill Ranks per Level</strong>: 4 +&nbsp;<a href=\"https://www.d20pfsrd.com/basics-ability-scores/ability-scores#TOC-Intelligence-Int-\">Int</a> modifier.</p>"
        },
        "tags": [],
        "changes": [],
        "links": {
          "children": [],
          "classAssociations": [
            {
              "id": "pf1.class-abilities.VjHjPja5QABBgRvR",
              "dataType": "compendium",
              "name": "Bonus Feat (MNK)",
              "img": "systems/pf1/icons/skills/blue_10.jpg",
              "hiddenLinks": {},
              "level": 1,
              "_index": 0
            },
            {
              "id": "pf1.class-abilities.JKJoHy5NveXGaZqv",
              "dataType": "compendium",
              "name": "Flurry of Blows",
              "img": "systems/pf1/icons/items/weapons/claw-blades.PNG",
              "hiddenLinks": {},
              "level": 1,
              "_index": 1
            },
            {
              "id": "pf1.class-abilities.2ausI8g6SsmbOpgF",
              "dataType": "compendium",
              "name": "Stunning Fist",
              "img": "systems/pf1/icons/skills/yellow_08.jpg",
              "hiddenLinks": {},
              "level": 1,
              "_index": 2
            },
            {
              "id": "pf1.class-abilities.a4SPdPuOFdmfJdHN",
              "dataType": "compendium",
              "name": "Unarmed Strike",
              "img": "systems/pf1/icons/skills/blood_11.jpg",
              "hiddenLinks": {},
              "level": 1,
              "_index": 3
            },
            {
              "id": "pf1.class-abilities.KQYCRLEdD4bGA5ak",
              "dataType": "compendium",
              "name": "Evasion",
              "img": "systems/pf1/icons/skills/blue_06.jpg",
              "hiddenLinks": {},
              "level": 2,
              "_index": 4
            },
            {
              "id": "pf1.class-abilities.Cc2eFfhJYlClCGEH",
              "dataType": "compendium",
              "name": "Improved Evasion",
              "img": "systems/pf1/icons/skills/blue_06.jpg",
              "hiddenLinks": {},
              "level": 9,
              "_index": 5
            },
            {
              "id": "pf1.class-abilities.CK5L0YJDENqBxLqv",
              "dataType": "compendium",
              "name": "Fast Movement (MNK)",
              "img": "systems/pf1/icons/feats/dodge.jpg",
              "hiddenLinks": {},
              "level": 3,
              "_index": 6
            },
            {
              "id": "pf1.class-abilities.E7enBZN7FCsoyIof",
              "dataType": "compendium",
              "name": "Maneuver Training",
              "img": "systems/pf1/icons/feats/athletic.jpg",
              "hiddenLinks": {},
              "level": 3,
              "_index": 7
            },
            {
              "id": "pf1.class-abilities.8VUae7CIgCidvSfg",
              "dataType": "compendium",
              "name": "Still Mind",
              "img": "systems/pf1/icons/feats/blind-fight.jpg",
              "hiddenLinks": {},
              "level": 3,
              "_index": 8
            },
            {
              "id": "pf1.class-abilities.2Og23i3rRXu5QQlg",
              "dataType": "compendium",
              "name": "ki Pool",
              "img": "systems/pf1/icons/skills/red_09.jpg",
              "hiddenLinks": {},
              "level": 4,
              "_index": 9
            },
            {
              "id": "pf1.class-abilities.M4bXVPXouXroIt90",
              "dataType": "compendium",
              "name": "Slow Fall",
              "img": "systems/pf1/icons/skills/red_05.jpg",
              "hiddenLinks": {},
              "level": 4,
              "_index": 10
            },
            {
              "id": "pf1.class-abilities.WJEF9WHs27kaFYJL",
              "dataType": "compendium",
              "name": "High Jump",
              "img": "systems/pf1/icons/skills/yellow_13.jpg",
              "hiddenLinks": {},
              "level": 5,
              "_index": 11
            },
            {
              "id": "pf1.class-abilities.82G7gl4C1AvtSHI4",
              "dataType": "compendium",
              "name": "Purity of Body",
              "img": "systems/pf1/icons/skills/blue_35.jpg",
              "hiddenLinks": {},
              "level": 5,
              "_index": 12
            },
            {
              "id": "pf1.class-abilities.nRffrQSKTqjeBAO5",
              "dataType": "compendium",
              "name": "Diamond Body",
              "img": "systems/pf1/icons/skills/blue_28.jpg",
              "hiddenLinks": {},
              "level": 11,
              "_index": 13
            },
            {
              "id": "pf1.class-abilities.XJtvco1XWggmr5LU",
              "dataType": "compendium",
              "name": "Abundant Step",
              "img": "systems/pf1/icons/spells/protect-blue-2.jpg",
              "hiddenLinks": {},
              "level": 12,
              "_index": 14
            },
            {
              "id": "pf1.class-abilities.bCdFkzKiVg52ufhu",
              "dataType": "compendium",
              "name": "Diamond Soul",
              "img": "systems/pf1/icons/spells/ice-blue-1.jpg",
              "hiddenLinks": {},
              "level": 13,
              "_index": 15
            },
            {
              "id": "pf1.class-abilities.n4SWyKVcdmZK4t7d",
              "dataType": "compendium",
              "name": "Quivering Palm",
              "img": "systems/pf1/icons/feats/combat-casting.jpg",
              "hiddenLinks": {},
              "level": 15,
              "_index": 16
            },
            {
              "id": "pf1.class-abilities.5JlthJkVGEHPZypG",
              "dataType": "compendium",
              "name": "Timeless Body",
              "img": "systems/pf1/icons/skills/green_15.jpg",
              "hiddenLinks": {},
              "level": 17,
              "_index": 17
            },
            {
              "id": "pf1.class-abilities.NKzRm45051DUHkd5",
              "dataType": "compendium",
              "name": "Tongue of the Sun and Moon",
              "img": "systems/pf1/icons/feats/natural-spell.jpg",
              "hiddenLinks": {},
              "level": 17,
              "_index": 18
            },
            {
              "id": "pf1.class-abilities.dtnkUkinLVIl1b2T",
              "dataType": "compendium",
              "name": "Empty Body",
              "img": "systems/pf1/icons/feats/blinding-critical.jpg",
              "hiddenLinks": {},
              "level": 19,
              "_index": 19
            },
            {
              "id": "pf1.class-abilities.NNEU7hzPSu2LTyZv",
              "dataType": "compendium",
              "name": "Perfect Self",
              "img": "systems/pf1/icons/feats/exhausting-critical.jpg",
              "hiddenLinks": {},
              "level": 20,
              "_index": 20
            },
            {
              "id": "pf1.class-abilities.4zVndIJ8NMWWzl1T",
              "dataType": "compendium",
              "name": "AC Bonus (MNK)",
              "img": "systems/pf1/icons/spells/fog-air-1.jpg",
              "hiddenLinks": {},
              "level": 1,
              "_index": 21
            }
          ]
        },
        "tag": "monk",
        "useCustomTag": true,
        "armorProf": {
          "value": []
        },
        "weaponProf": {
          "value": [],
          "custom": "Brass Knuckles;Cestus;Club;Crossbow (light or heavy);Dagger;Handaxe;Javelin;Kama;Nunchaku;Quarterstaff;Sai;Shortspear;Short Sword;Shuriken;Siangham;Sling;Spear;Temple Sword"
        },
        "flags": {
          "boolean": [],
          "dictionary": []
        },
        "scriptCalls": [],
        "bab": "med",
        "skillsPerLevel": 4,
        "savingThrows": {
          "fort": {
            "value": "high"
          },
          "ref": {
            "value": "high"
          },
          "will": {
            "value": "high"
          }
        },
        "classSkills": {
          "acr": true,
          "apr": false,
          "art": false,
          "blf": false,
          "clm": true,
          "crf": true,
          "dip": false,
          "dev": false,
          "dis": false,
          "esc": true,
          "fly": false,
          "han": false,
          "hea": false,
          "int": true,
          "kar": false,
          "kdu": false,
          "ken": false,
          "kge": false,
          "khi": true,
          "klo": false,
          "kna": false,
          "kno": false,
          "kpl": false,
          "kre": true,
          "lin": false,
          "lor": false,
          "per": true,
          "prf": true,
          "pro": true,
          "rid": true,
          "sen": true,
          "slt": false,
          "spl": false,
          "ste": true,
          "sur": false,
          "swm": true,
          "umd": false
        }
      },
      "effects": [],
      "folder": null,
      "sort": 0,
      "permission": {
        "default": 0
      },
      "flags": {}
    },
    {
      "_id": "S38eYYsK7pRhPbwg",
      "name": "Humanoid (Kasatha)",
      "type": "class",
      "img": "systems/pf1/icons/skills/blue_35.jpg",
      "data": {
        "description": {
          "value": "<p>A humanoid usually has two arms, two legs, and one head, or a human-like torso, arms, and a head. Humanoids have few or no supernatural or extraordinary abilities, but most can speak and usually have well-developed societies. They are usually Small or Medium (with the exception of giants). Every humanoid creature also has a specific subtype to match its race, such as human, giant, goblinoid, reptilian, or tengu.</p>\n<p>Humanoids with 1 Hit Die exchange the features of their humanoid Hit Die for the class features of a PC or NPC class. Humanoids of this sort are typically presented as 1st-level warriors, which means they have average combat ability and poor saving throws. Humanoids with more than 1 Hit Die are the only humanoids who make use of the features of the humanoid type.</p>\n<h2><span id=\"Features\">Features</span></h2>\n<p>A humanoid has the following features (unless otherwise noted in a creature’s entry).</p>\n<ul>\n<li>d8 Hit Die, or by character class.</li>\n<li>Base attack bonus equal to 3/4 total Hit Dice (medium progression).</li>\n<li>One good save, usually&nbsp;<a href=\"https://www.d20pfsrd.com/gamemastering/combat#TOC-Reflex\" rel=\"nofollow\">Reflex</a>.</li>\n<li>Skill points equal to 2 + Int modifier (minimum 1) per Hit Die or by character class. The following are class skills for humanoids without a character class: <a href=\"https://www.d20pfsrd.com/skills/climb\" rel=\"nofollow\">Climb</a>, <a href=\"https://www.d20pfsrd.com/skills/craft\" rel=\"nofollow\">Craft</a>, <a href=\"https://www.d20pfsrd.com/skills/handle-animal\" rel=\"nofollow\">Handle Animal</a>, <a href=\"https://www.d20pfsrd.com/skills/heal\" rel=\"nofollow\">Heal</a>, <a href=\"https://www.d20pfsrd.com/skills/profession\" rel=\"nofollow\">Profession</a>, <a href=\"https://www.d20pfsrd.com/skills/ride\" rel=\"nofollow\">Ride</a>, and <a href=\"https://www.d20pfsrd.com/skills/survival\" rel=\"nofollow\">Survival</a>. Humanoids with a character class use their class’s skill list instead.</li>\n</ul>\n<h2><span id=\"Traits\"><a name=\"TOC-Traits\"></a>Traits</span></h2>\n<p>A humanoid possesses the following traits (unless otherwise noted in a creature’s entry).</p>\n<ul>\n<li>Proficient with all simple weapons, or by character class.</li>\n<li>Proficient with whatever type of armor (light, medium, or heavy) it is described as wearing, or by character class. If a humanoid does not have a class and wears&nbsp;<a href=\"https://www.d20pfsrd.com/basics-ability-scores/glossary#TOC-Armor-Bonus\">armor</a>, it is proficient with that type of armor and all lighter types. Humanoids not indicated as wearing armor are not proficient with armor. Humanoids are proficient with shields if they are proficient with any form of armor.</li>\n<li>Humanoids breathe, eat, and sleep.</li>\n</ul>"
        },
        "tags": [],
        "changes": [],
        "links": "",
        "tag": "humanoid",
        "useCustomTag": true,
        "armorProf": {
          "value": []
        },
        "weaponProf": {
          "value": []
        },
        "flags": {
          "boolean": [],
          "dictionary": []
        },
        "scriptCalls": [],
        "classType": "racial",
        "level": 0,
        "hp": 0,
        "bab": "med",
        "skillsPerLevel": 2,
        "savingThrows": {
          "ref": {
            "value": "high"
          }
        },
        "classSkills": {
          "acr": false,
          "apr": false,
          "art": false,
          "blf": false,
          "clm": true,
          "crf": true,
          "dip": false,
          "dev": false,
          "dis": false,
          "esc": false,
          "fly": false,
          "han": true,
          "hea": true,
          "int": false,
          "kar": false,
          "kdu": false,
          "ken": false,
          "kge": false,
          "khi": false,
          "klo": false,
          "kna": false,
          "kno": false,
          "kpl": false,
          "kre": false,
          "lin": false,
          "lor": false,
          "per": false,
          "prf": false,
          "pro": true,
          "rid": true,
          "sen": false,
          "slt": false,
          "spl": false,
          "ste": false,
          "sur": true,
          "swm": false,
          "umd": false
        }
      },
      "effects": [],
      "folder": null,
      "sort": 0,
      "permission": {
        "default": 0
      },
      "flags": {}
    },
    {
      "_id": "h9nHYLxXvIXBTmup",
      "name": "Combat Reflexes",
      "type": "feat",
      "img": "systems/pf1/icons/feats/combat-reflexes.jpg",
      "data": {
        "description": {
          "value": "\n                <i>You can make additional attacks of opportunity.</i>\n                <br />\n                <br />\n                \n                <p><b>Benefits</b></p>\n                <p><p class=\"stat-block-1\"> You may make a number of additional attacks of opportunity per round equal to your Dexterity bonus. With this feat, you may also make attacks of opportunity while flat-footed.</p></p>\n                \n            <br />\n                <p><b>Normal</b></p>\n                <p><p class=\"stat-block-1\"> A character without this feat can make only one attack of opportunity per round and can't make attacks of opportunity while flat-footed.</p></p>\n                \n            <br />\n                <p><b>Special</b></p>\n                <p><p class=\"stat-block-1\"> The Combat Reflexes feat does not allow a rogue to use her opportunist ability more than once per round.</p></p>\n                \n            \n            "
        },
        "tags": [
          [
            "Combat"
          ],
          [
            "Offensive"
          ]
        ],
        "measureTemplate": {
          "size": "0"
        },
        "actionType": "",
        "damage": {
          "parts": [],
          "critParts": [],
          "nonCritParts": []
        },
        "attackParts": [],
        "effectNotes": [],
        "attackNotes": [],
        "changes": [],
        "contextNotes": [],
        "links": {
          "children": [],
          "charges": []
        },
        "tag": "combatReflexes",
        "armorProf": {
          "value": []
        },
        "weaponProf": {
          "value": []
        },
        "flags": {
          "boolean": [],
          "dictionary": []
        },
        "scriptCalls": [],
        "associations": {
          "classes": []
        }
      },
      "effects": [],
      "folder": null,
      "sort": 0,
      "permission": {
        "default": 0
      },
      "flags": {}
    },
    {
      "_id": "2aTFNMs3pW6nUBlr",
      "name": "Improved Unarmed Strike",
      "type": "feat",
      "img": "systems/pf1/icons/feats/improved-unarmed-strike.jpg",
      "data": {
        "description": {
          "value": "\n                <i>You are skilled at fighting while unarmed.</i>\n                <br />\n                <br />\n                \n                <p><b>Benefits</b></p>\n                <p><p class=\"stat-block-1\"> You are considered to be armed even when unarmed&mdash;you do not provoke attacks of opportunity when you attack foes while unarmed. Your unarmed strikes can deal lethal or nonlethal damage, at your choice.</p></p>\n                \n            <br />\n                <p><b>Normal</b></p>\n                <p><p class=\"stat-block-1\"> Without this feat, you are considered unarmed when attacking with an unarmed strike, and you can deal only nonlethal damage with such an attack.</p></p>\n                \n            \n            "
        },
        "tags": [
          [
            "Combat"
          ],
          [
            "Unarmed"
          ],
          [
            "Offensive"
          ]
        ],
        "measureTemplate": {
          "size": "0"
        },
        "actionType": "",
        "damage": {
          "parts": [],
          "critParts": [],
          "nonCritParts": []
        },
        "attackParts": [],
        "effectNotes": [],
        "attackNotes": [],
        "changes": [],
        "contextNotes": [],
        "links": {
          "children": [],
          "charges": []
        },
        "tag": "improvedUnarmedStrike",
        "armorProf": {
          "value": []
        },
        "weaponProf": {
          "value": []
        },
        "flags": {
          "boolean": [],
          "dictionary": []
        },
        "scriptCalls": [],
        "associations": {
          "classes": []
        }
      },
      "effects": [],
      "folder": null,
      "sort": 0,
      "permission": {
        "default": 0
      },
      "flags": {}
    },
    {
      "_id": "GsjouI6B8X7BA5wN",
      "name": "Stunning Fist",
      "type": "feat",
      "img": "systems/pf1/icons/feats/stunning-fist.jpg",
      "data": {
        "description": {
          "value": "\n                <i>You know just where to strike to temporarily stun a foe.</i>\n                <br />\n                <br />\n                \n                <p><b>Prerequisites</b></p>\n                <p> Dex 13, Wis 13, Improved Unarmed Strike, base attack bonus +8.</p>\n                \n            <br />\n                <p><b>Benefits</b></p>\n                <p><p class=\"stat-block-1\"> You must declare that you are using this feat before you make your attack roll (thus, a failed attack roll ruins the attempt). Stunning Fist forces a foe damaged by your unarmed attack to make a Fortitude saving throw (DC 10 + 1/2 your character level + your Wis modifier), in addition to dealing damage normally. A defender who fails this saving throw is stunned for 1 round (until just before your next turn). A stunned character drops everything held, can't take actions, loses any Dexterity bonus to AC, and takes a &ndash;2 penalty to AC. You may attempt a stunning attack once per day for every four levels you have attained (but see Special), and no more than once per round. Constructs, oozes, plants, undead, incorporeal creatures, and creatures immune to critical hits cannot be stunned.</p></p>\n                \n            <br />\n                <p><b>Special</b></p>\n                <p><p class=\"stat-block-1\"> A monk receives Stunning Fist as a bonus feat at 1st level, even if he does not meet the prerequisites. A monk may attempt a stunning attack a number of times per day equal to his monk level, plus one more time per day for every four levels he has in classes other than monk.</p></p>\n                \n            \n            "
        },
        "tags": [
          [
            "Combat"
          ],
          [
            "Unarmed"
          ],
          [
            "Offensive"
          ]
        ],
        "measureTemplate": {
          "size": "0"
        },
        "actionType": "",
        "damage": {
          "parts": [],
          "critParts": [],
          "nonCritParts": []
        },
        "attackParts": [],
        "effectNotes": [],
        "attackNotes": [],
        "changes": [],
        "contextNotes": [],
        "links": {
          "children": [],
          "charges": []
        },
        "tag": "stunningFist",
        "armorProf": {
          "value": []
        },
        "weaponProf": {
          "value": []
        },
        "flags": {
          "boolean": [],
          "dictionary": []
        },
        "scriptCalls": [],
        "associations": {
          "classes": []
        }
      },
      "effects": [],
      "folder": null,
      "sort": 0,
      "permission": {
        "default": 0
      },
      "flags": {}
    },
    {
      "_id": "vWiTqHC4Y3Xn1Pme",
      "name": "Weapon Finesse",
      "type": "feat",
      "img": "systems/pf1/icons/feats/weapon-finesse.jpg",
      "data": {
        "description": {
          "value": "\n                <i>You are trained in using your agility in melee combat, as opposed to brute strength.</i>\n                <br />\n                <br />\n                \n                <p><b>Benefits</b></p>\n                <p><p class=\"stat-block-1\"> With a light weapon, rapier, whip, or spiked chain made for a creature of your size category, you may use your Dexterity modifier instead of your Strength modifier on attack rolls. If you carry a shield, its armor check penalty applies to your attack rolls.</p></p>\n                \n            <br />\n                <p><b>Special</b></p>\n                <p><p class=\"stat-block-1\"> Natural weapons are considered light weapons.</p></p>\n                \n            \n            "
        },
        "tags": [
          [
            "Combat"
          ],
          [
            "Weapon"
          ]
        ],
        "measureTemplate": {
          "size": "0"
        },
        "actionType": "",
        "damage": {
          "parts": [],
          "critParts": [],
          "nonCritParts": []
        },
        "attackParts": [],
        "effectNotes": [],
        "attackNotes": [],
        "changes": [],
        "contextNotes": [],
        "links": {
          "children": [],
          "charges": []
        },
        "tag": "weaponFinesse",
        "armorProf": {
          "value": []
        },
        "weaponProf": {
          "value": []
        },
        "flags": {
          "boolean": [],
          "dictionary": []
        },
        "scriptCalls": [],
        "associations": {
          "classes": []
        }
      },
      "effects": [],
      "folder": null,
      "sort": 0,
      "permission": {
        "default": 0
      },
      "flags": {}
    },
    {
      "_id": "tdsi07kikd7zxjgt",
      "name": "Special Quality: Desert Runner",
      "type": "feat",
      "img": "systems/pf1/icons/skills/yellow_36.jpg",
      "data": {
        "description": {
          "value": "sbc | Placeholder for Special Qualities, which in most statblocks are listed under SQ in the statistics block, but described in the Special Abilities. Remove duplicates as needed!"
        },
        "tags": [],
        "damage": {
          "parts": [],
          "critParts": [],
          "nonCritParts": []
        },
        "attackParts": [],
        "effectNotes": [],
        "attackNotes": [],
        "changes": [],
        "contextNotes": [],
        "links": {
          "children": [],
          "charges": []
        },
        "armorProf": {
          "value": []
        },
        "weaponProf": {
          "value": []
        },
        "flags": {
          "boolean": [],
          "dictionary": []
        },
        "scriptCalls": [],
        "featType": "misc",
        "associations": {
          "classes": []
        }
      },
      "effects": [],
      "folder": null,
      "sort": 0,
      "permission": {
        "default": 0
      },
      "flags": {}
    },
    {
      "_id": "r55j4awbs8n0tkk2",
      "name": "Special Quality: Desert Stride",
      "type": "feat",
      "img": "systems/pf1/icons/skills/yellow_36.jpg",
      "data": {
        "description": {
          "value": "sbc | Placeholder for Special Qualities, which in most statblocks are listed under SQ in the statistics block, but described in the Special Abilities. Remove duplicates as needed!"
        },
        "tags": [],
        "damage": {
          "parts": [],
          "critParts": [],
          "nonCritParts": []
        },
        "attackParts": [],
        "effectNotes": [],
        "attackNotes": [],
        "changes": [],
        "contextNotes": [],
        "links": {
          "children": [],
          "charges": []
        },
        "armorProf": {
          "value": []
        },
        "weaponProf": {
          "value": []
        },
        "flags": {
          "boolean": [],
          "dictionary": []
        },
        "scriptCalls": [],
        "featType": "misc",
        "associations": {
          "classes": []
        }
      },
      "effects": [],
      "folder": null,
      "sort": 0,
      "permission": {
        "default": 0
      },
      "flags": {}
    },
    {
      "_id": "qgm8yoh0pgoxiy7w",
      "name": "Special Quality: Jumper",
      "type": "feat",
      "img": "systems/pf1/icons/skills/yellow_36.jpg",
      "data": {
        "description": {
          "value": "sbc | Placeholder for Special Qualities, which in most statblocks are listed under SQ in the statistics block, but described in the Special Abilities. Remove duplicates as needed!"
        },
        "tags": [],
        "damage": {
          "parts": [],
          "critParts": [],
          "nonCritParts": []
        },
        "attackParts": [],
        "effectNotes": [],
        "attackNotes": [],
        "changes": [],
        "contextNotes": [],
        "links": {
          "children": [],
          "charges": []
        },
        "armorProf": {
          "value": []
        },
        "weaponProf": {
          "value": []
        },
        "flags": {
          "boolean": [],
          "dictionary": []
        },
        "scriptCalls": [],
        "featType": "misc",
        "associations": {
          "classes": []
        }
      },
      "effects": [],
      "folder": null,
      "sort": 0,
      "permission": {
        "default": 0
      },
      "flags": {}
    },
    {
      "_id": "rkpu78plmjgy393v",
      "name": "Special Quality: Multi-armed",
      "type": "feat",
      "img": "systems/pf1/icons/skills/yellow_36.jpg",
      "data": {
        "description": {
          "value": "sbc | Placeholder for Special Qualities, which in most statblocks are listed under SQ in the statistics block, but described in the Special Abilities. Remove duplicates as needed!"
        },
        "tags": [],
        "damage": {
          "parts": [],
          "critParts": [],
          "nonCritParts": []
        },
        "attackParts": [],
        "effectNotes": [],
        "attackNotes": [],
        "changes": [],
        "contextNotes": [],
        "links": {
          "children": [],
          "charges": []
        },
        "armorProf": {
          "value": []
        },
        "weaponProf": {
          "value": []
        },
        "flags": {
          "boolean": [],
          "dictionary": []
        },
        "scriptCalls": [],
        "featType": "misc",
        "associations": {
          "classes": []
        }
      },
      "effects": [],
      "folder": null,
      "sort": 0,
      "permission": {
        "default": 0
      },
      "flags": {}
    },
    {
      "_id": "5wddnk01lvldgwtc",
      "name": "Special Quality: Stalker",
      "type": "feat",
      "img": "systems/pf1/icons/skills/yellow_36.jpg",
      "data": {
        "description": {
          "value": "sbc | Placeholder for Special Qualities, which in most statblocks are listed under SQ in the statistics block, but described in the Special Abilities. Remove duplicates as needed!"
        },
        "tags": [],
        "damage": {
          "parts": [],
          "critParts": [],
          "nonCritParts": []
        },
        "attackParts": [],
        "effectNotes": [],
        "attackNotes": [],
        "changes": [],
        "contextNotes": [],
        "links": {
          "children": [],
          "charges": []
        },
        "armorProf": {
          "value": []
        },
        "weaponProf": {
          "value": []
        },
        "flags": {
          "boolean": [],
          "dictionary": []
        },
        "scriptCalls": [],
        "featType": "misc",
        "associations": {
          "classes": []
        }
      },
      "effects": [],
      "folder": null,
      "sort": 0,
      "permission": {
        "default": 0
      },
      "flags": {}
    },
    {
      "_id": "uk1ifyjwczccflk3",
      "name": "Sai",
      "type": "attack",
      "img": null,
      "data": {
        "tags": [],
        "activation": {
          "type": "attack"
        },
        "unchainedAction": {
          "activation": {
            "type": "attack"
          }
        },
        "duration": {
          "units": "inst"
        },
        "range": {
          "value": "",
          "units": "melee"
        },
        "attackName": "Sai",
        "actionType": "mwak",
        "attackBonus": "2",
        "damage": {
          "parts": [
            [
              "1d4+0",
              "B"
            ]
          ],
          "critParts": [],
          "nonCritParts": []
        },
        "attackParts": [],
        "ability": {
          "attack": "str",
          "damage": "str"
        },
        "effectNotes": [],
        "attackNotes": [
          "sai +3 (1d4+1 )",
          "Weapon Qualities: [disarm, monk]"
        ],
        "links": {
          "children": [],
          "charges": [],
          "ammunition": []
        },
        "flags": {
          "boolean": [],
          "dictionary": []
        },
        "scriptCalls": [],
        "primaryAttack": false,
        "conditionals": []
      },
      "effects": [],
      "folder": null,
      "sort": 0,
      "permission": {
        "default": 0
      },
      "flags": {}
    },
    {
      "_id": "2gw2g3kzvgvk4bni",
      "name": "Unarmed Strike",
      "type": "attack",
      "img": null,
      "data": {
        "tags": [],
        "activation": {
          "type": "attack"
        },
        "unchainedAction": {
          "activation": {
            "type": "attack"
          }
        },
        "duration": {
          "units": "inst"
        },
        "range": {
          "value": "",
          "units": "melee"
        },
        "attackName": "Unarmed Strike",
        "actionType": "mwak",
        "attackBonus": "2",
        "damage": {
          "parts": [
            [
              "1d6+0",
              "B"
            ]
          ],
          "critParts": [],
          "nonCritParts": []
        },
        "attackParts": [],
        "ability": {
          "attack": "str",
          "damage": "str"
        },
        "effectNotes": [],
        "attackNotes": [
          "unarmed strike +3 (1d6+1 )",
          "Weapon Qualities: [nonlethal]"
        ],
        "links": {
          "children": [],
          "charges": [],
          "ammunition": []
        },
        "flags": {
          "boolean": [],
          "dictionary": []
        },
        "scriptCalls": [],
        "primaryAttack": false,
        "conditionals": []
      },
      "effects": [],
      "folder": null,
      "sort": 0,
      "permission": {
        "default": 0
      },
      "flags": {}
    },
    {
      "_id": "qlld63p31vnn88dg",
      "name": "Flurry Of Blows",
      "type": "attack",
      "img": null,
      "data": {
        "tags": [],
        "activation": {
          "type": "attack"
        },
        "unchainedAction": {
          "activation": {
            "type": "attack"
          }
        },
        "duration": {
          "units": "inst"
        },
        "range": {
          "value": "",
          "units": "melee"
        },
        "attackName": "Flurry Of Blows",
        "actionType": "mwak",
        "attackBonus": "1",
        "damage": {
          "parts": [
            [
              "1d6+0",
              ""
            ]
          ],
          "critParts": [],
          "nonCritParts": []
        },
        "attackParts": [
          [
            -5,
            "Iterative Attack with -5"
          ]
        ],
        "ability": {
          "attack": "str",
          "damage": "str"
        },
        "effectNotes": [],
        "attackNotes": [
          "flurry of blows +2/+5 (1d6+1 )"
        ],
        "links": {
          "children": [],
          "charges": [],
          "ammunition": []
        },
        "flags": {
          "boolean": [],
          "dictionary": []
        },
        "scriptCalls": [],
        "primaryAttack": false,
        "conditionals": []
      },
      "effects": [],
      "folder": null,
      "sort": 0,
      "permission": {
        "default": 0
      },
      "flags": {}
    },
    {
      "_id": "hm1u37vwfa6e5okd",
      "name": "Special Attack: Flurry Of Blows",
      "type": "attack",
      "img": "systems/pf1/icons/skills/yellow_36.jpg",
      "data": {
        "description": {
          "value": "sbc | Placeholder for Special Attacks, which in most statblocks are listed under 'Special Attacks' in the statistics block, but are described in the 'Special Abilities' block. Remove duplicates as needed!"
        },
        "tags": [],
        "damage": {
          "parts": [],
          "critParts": [],
          "nonCritParts": []
        },
        "attackParts": [],
        "effectNotes": [],
        "attackNotes": [],
        "links": {
          "children": [],
          "charges": [],
          "ammunition": []
        },
        "flags": {
          "boolean": [],
          "dictionary": []
        },
        "scriptCalls": [],
        "attackType": "misc",
        "conditionals": []
      },
      "effects": [],
      "folder": null,
      "sort": 0,
      "permission": {
        "default": 0
      },
      "flags": {}
    },
    {
      "_id": "acuo9rcsw1pgnl7p",
      "name": "Special Attack: Stunning Fist (1/day, Dc 13)",
      "type": "attack",
      "img": "systems/pf1/icons/skills/yellow_36.jpg",
      "data": {
        "description": {
          "value": "sbc | Placeholder for Special Attacks, which in most statblocks are listed under 'Special Attacks' in the statistics block, but are described in the 'Special Abilities' block. Remove duplicates as needed!"
        },
        "tags": [],
        "damage": {
          "parts": [],
          "critParts": [],
          "nonCritParts": []
        },
        "attackParts": [],
        "effectNotes": [],
        "attackNotes": [],
        "links": {
          "children": [],
          "charges": [],
          "ammunition": []
        },
        "flags": {
          "boolean": [],
          "dictionary": []
        },
        "scriptCalls": [],
        "attackType": "misc",
        "conditionals": []
      },
      "effects": [],
      "folder": null,
      "sort": 0,
      "permission": {
        "default": 0
      },
      "flags": {}
    },
    {
      "_id": "mtnnk91gudk4wnos",
      "name": "Ecology",
      "type": "feat",
      "img": "icons/environment/wilderness/tree-oak.webp",
      "data": {
        "description": {
          "value": "<div><strong>Environment</strong>:  warm deserts</div><div><strong>Organization</strong>:  solitary, band (2-6), sect (2-20), or tribe (20-60)</div><div><strong>Treasure</strong>:  NPC gear (sais [2], other treasure)</div>"
        },
        "tags": [],
        "damage": {
          "parts": [],
          "critParts": [],
          "nonCritParts": []
        },
        "attackParts": [],
        "effectNotes": [],
        "attackNotes": [],
        "changes": [],
        "contextNotes": [],
        "links": {
          "children": [],
          "charges": []
        },
        "armorProf": {
          "value": []
        },
        "weaponProf": {
          "value": []
        },
        "flags": {
          "boolean": [],
          "dictionary": []
        },
        "scriptCalls": [],
        "featType": "misc",
        "associations": {
          "classes": []
        }
      },
      "effects": [],
      "folder": null,
      "sort": 0,
      "permission": {
        "default": 0
      },
      "flags": {}
    },
    {
      "_id": "vdwqt6141nsc583f",
      "name": "Desert Runner",
      "type": "feat",
      "img": "systems/pf1/icons/skills/yellow_36.jpg",
      "data": {
        "description": {
          "value": "A kasatha has a +4 racial bonus on Constitution checks and Fortitude saves to avoid fatigue, exhaustion, and other ill effects from running, forced marches, starvation, thirst, and hot or cold environments."
        },
        "tags": [],
        "damage": {
          "parts": [],
          "critParts": [],
          "nonCritParts": []
        },
        "attackParts": [],
        "effectNotes": [],
        "attackNotes": [],
        "changes": [],
        "contextNotes": [],
        "links": {
          "children": [],
          "charges": []
        },
        "armorProf": {
          "value": []
        },
        "weaponProf": {
          "value": []
        },
        "flags": {
          "boolean": [],
          "dictionary": []
        },
        "scriptCalls": [],
        "featType": "classFeat",
        "associations": {
          "classes": []
        },
        "abilityType": "ex"
      },
      "effects": [],
      "folder": null,
      "sort": 0,
      "permission": {
        "default": 0
      },
      "flags": {}
    },
    {
      "_id": "jzz94sr2aijrbnwr",
      "name": "Desert Stride",
      "type": "feat",
      "img": "systems/pf1/icons/skills/yellow_36.jpg",
      "data": {
        "description": {
          "value": "A kasatha moves through nonmagical difficult terrain in desert environments at normal speed."
        },
        "tags": [],
        "damage": {
          "parts": [],
          "critParts": [],
          "nonCritParts": []
        },
        "attackParts": [],
        "effectNotes": [],
        "attackNotes": [],
        "changes": [],
        "contextNotes": [],
        "links": {
          "children": [],
          "charges": []
        },
        "armorProf": {
          "value": []
        },
        "weaponProf": {
          "value": []
        },
        "flags": {
          "boolean": [],
          "dictionary": []
        },
        "scriptCalls": [],
        "featType": "classFeat",
        "associations": {
          "classes": []
        },
        "abilityType": "ex"
      },
      "effects": [],
      "folder": null,
      "sort": 0,
      "permission": {
        "default": 0
      },
      "flags": {}
    },
    {
      "_id": "u6d7al7qmiil0t3c",
      "name": "Jumper",
      "type": "feat",
      "img": "systems/pf1/icons/skills/yellow_36.jpg",
      "data": {
        "description": {
          "value": "A kasatha is always considered to have a running start when attempting Acrobatics checks to jump."
        },
        "tags": [],
        "damage": {
          "parts": [],
          "critParts": [],
          "nonCritParts": []
        },
        "attackParts": [],
        "effectNotes": [],
        "attackNotes": [],
        "changes": [],
        "contextNotes": [],
        "links": {
          "children": [],
          "charges": []
        },
        "armorProf": {
          "value": []
        },
        "weaponProf": {
          "value": []
        },
        "flags": {
          "boolean": [],
          "dictionary": []
        },
        "scriptCalls": [],
        "featType": "classFeat",
        "associations": {
          "classes": []
        },
        "abilityType": "ex"
      },
      "effects": [],
      "folder": null,
      "sort": 0,
      "permission": {
        "default": 0
      },
      "flags": {}
    },
    {
      "_id": "dgw2su51qvf3obmr",
      "name": "Multi-armed",
      "type": "feat",
      "img": "systems/pf1/icons/skills/yellow_36.jpg",
      "data": {
        "description": {
          "value": "A kasatha has four arms. One hand is considered its primary hand; all others are considered off hands. It can use any of its hands for other purposes that require free hands."
        },
        "tags": [],
        "damage": {
          "parts": [],
          "critParts": [],
          "nonCritParts": []
        },
        "attackParts": [],
        "effectNotes": [],
        "attackNotes": [],
        "changes": [],
        "contextNotes": [],
        "links": {
          "children": [],
          "charges": []
        },
        "armorProf": {
          "value": []
        },
        "weaponProf": {
          "value": []
        },
        "flags": {
          "boolean": [],
          "dictionary": []
        },
        "scriptCalls": [],
        "featType": "classFeat",
        "associations": {
          "classes": []
        },
        "abilityType": "ex"
      },
      "effects": [],
      "folder": null,
      "sort": 0,
      "permission": {
        "default": 0
      },
      "flags": {}
    },
    {
      "_id": "dbdslzpg1jvfarfn",
      "name": "Stalker",
      "type": "feat",
      "img": "systems/pf1/icons/skills/yellow_36.jpg",
      "data": {
        "description": {
          "value": "Perception and Stealth are class skills for a kasatha."
        },
        "tags": [],
        "damage": {
          "parts": [],
          "critParts": [],
          "nonCritParts": []
        },
        "attackParts": [],
        "effectNotes": [],
        "attackNotes": [],
        "changes": [],
        "contextNotes": [],
        "links": {
          "children": [],
          "charges": []
        },
        "armorProf": {
          "value": []
        },
        "weaponProf": {
          "value": []
        },
        "flags": {
          "boolean": [],
          "dictionary": []
        },
        "scriptCalls": [],
        "featType": "classFeat",
        "associations": {
          "classes": []
        },
        "abilityType": "ex"
      },
      "effects": [],
      "folder": null,
      "sort": 0,
      "permission": {
        "default": 0
      },
      "flags": {}
    },
    {
      "_id": "aMaot6R8HqSmqbgW",
      "name": "sbc | Conversion Buff",
      "type": "buff",
      "img": "systems/pf1/icons/skills/yellow_36.jpg",
      "data": {
        "description": {
          "value": "<h2>sbc | Conversion Buff</h2>\n                        This Buff was created by <strong>sbc</strong> to compensate for differences between the input and the values FoundryVTT calculates automatically.\n                        <br><br>\n                        Especially when the pathfinder system gets upgraded, entries in compendiums get updated or foundry changes in some way, this buff may become outdated.\n                        <br><br>\n                        For most mooks the conversion should more or less work, but for important NPCs or creatures it is adviced to double check the conversion manually."
        },
        "tags": [],
        "changes": [
          {
            "formula": "-13",
            "modifier": "untypedPerm",
            "operator": "add",
            "priority": 0,
            "subTarget": "wis",
            "target": "ability",
            "value": -13,
            "id": "8163bn3h"
          },
          {
            "formula": "3",
            "modifier": "untypedPerm",
            "operator": "add",
            "priority": 0,
            "subTarget": "cmd",
            "target": "misc",
            "value": 3,
            "id": "vdpkzpx1"
          },
          {
            "formula": "2",
            "modifier": "dodge",
            "operator": "add",
            "priority": 0,
            "subTarget": "ac",
            "target": "ac",
            "value": 2,
            "id": "3dl6tlms"
          },
          {
            "formula": "1",
            "modifier": "untypedPerm",
            "operator": "add",
            "priority": 0,
            "subTarget": "mhp",
            "target": "misc",
            "value": 1,
            "id": "2fisdotu"
          },
          {
            "formula": "-2",
            "modifier": "untypedPerm",
            "operator": "add",
            "priority": 0,
            "subTarget": "ref",
            "target": "savingThrows",
            "value": -2,
            "id": "3nbfd4eg"
          },
          {
            "formula": "1",
            "modifier": "untypedPerm",
            "operator": "add",
            "priority": 0,
            "subTarget": "aac",
            "target": "ac",
            "value": 1,
            "id": "do8c6w0z"
          },
          {
            "formula": "-1",
            "modifier": "untypedPerm",
            "operator": "add",
            "priority": 0,
            "subTarget": "skill.acr",
            "target": "skill",
            "value": -1,
            "id": "2aotr1y3"
          },
          {
            "formula": "-1",
            "modifier": "untypedPerm",
            "operator": "add",
            "priority": 0,
            "subTarget": "skill.esc",
            "target": "skill",
            "value": -1,
            "id": "9fkhzx2k"
          },
          {
            "formula": "2",
            "modifier": "untypedPerm",
            "operator": "add",
            "priority": 0,
            "subTarget": "skill.sur",
            "target": "skill",
            "value": 2,
            "id": "bi22fw6x"
          }
        ],
        "contextNotes": [],
        "links": {
          "children": []
        },
        "tag": "sbcConversionBuff",
        "useCustomTag": true,
        "flags": {
          "boolean": [],
          "dictionary": []
        },
        "scriptCalls": [],
        "buffType": "perm",
        "active": true,
        "hideFromToken": true
      },
      "effects": [],
      "folder": null,
      "sort": 0,
      "permission": {
        "default": 0,
        "iM1ACTqH0Ml6HJtd": 3
      },
      "flags": {}
    }
  ],
  "effects": [],
  "folder": null,
  "sort": 0,
  "permission": {
    "default": 0
  },
  "flags": {}
}