{
  "_id": "stvj5zjdllpeed22",
  "name": "Conjure Black Pudding",
  "type": "spell",
  "img": "systems/pf1/icons/misc/magic-swirl.png",
  "data": {
    "tags": [],
    "actions": [
      {
        "_id": "xr9d4nixcb6vpw72",
        "name": "Use",
        "img": "systems/pf1/icons/misc/magic-swirl.png",
        "description": "",
        "activation": {
          "cost": 1,
          "type": "round"
        },
        "unchainedAction": {
          "activation": {
            "cost": 3,
            "type": "action"
          }
        },
        "duration": {
          "value": "1 round/level (D)",
          "units": ""
        },
        "target": {
          "value": ""
        },
        "range": {
          "value": null,
          "units": "close",
          "maxIncrements": 1,
          "minValue": null,
          "minUnits": ""
        },
        "uses": {
          "autoDeductCharges": true,
          "autoDeductChargesCost": "1",
          "per": "",
          "value": 0,
          "maxFormula": ""
        },
        "measureTemplate": {
          "type": "",
          "size": "0",
          "overrideColor": false,
          "customColor": "",
          "overrideTexture": false,
          "customTexture": ""
        },
        "attackName": "",
        "actionType": "other",
        "attackBonus": "",
        "critConfirmBonus": "",
        "damage": {
          "parts": [],
          "critParts": [],
          "nonCritParts": []
        },
        "attackParts": [],
        "formulaicAttacks": {
          "count": {
            "formula": ""
          },
          "bonus": {
            "formula": ""
          },
          "label": null
        },
        "formula": "",
        "ability": {
          "attack": "",
          "damage": "",
          "damageMult": 1,
          "critRange": 20,
          "critMult": 2
        },
        "save": {
          "dc": "0",
          "type": "",
          "description": ""
        },
        "effectNotes": [],
        "attackNotes": [],
        "soundEffect": "",
        "powerAttack": {
          "multiplier": "",
          "damageBonus": 2,
          "critMultiplier": 1
        },
        "naturalAttack": {
          "secondary": {
            "attackBonus": "-5",
            "damageMult": 0.5
          }
        },
        "attackType": "weapon",
        "nonlethal": false,
        "usesAmmo": false,
        "spellEffect": "one summoned black pudding",
        "spellArea": "",
        "conditionals": [],
        "enh": {
          "override": false,
          "value": 0
        }
      }
    ],
    "uses": {
      "per": ""
    },
    "attackNotes": [],
    "effectNotes": [],
    "links": {
      "children": []
    },
    "flags": {
      "boolean": [],
      "dictionary": []
    },
    "scriptCalls": [],
    "learnedAt": {
      "class": [
        [
          "sorcerer/wizard",
          6
        ],
        [
          "summoner",
          5
        ],
        [
          "psychic",
          6
        ],
        [
          "unchained Summoner",
          5
        ]
      ],
      "domain": [],
      "subDomain": [],
      "elementalSchool": [],
      "bloodline": []
    },
    "level": 6,
    "school": "con",
    "subschool": "summoning",
    "types": "acid",
    "components": {
      "verbal": true,
      "somatic": true,
      "material": true
    },
    "materials": {
      "value": "a flask of acid worth 10 gp",
      "gpValue": 10
    },
    "spellbook": "",
    "preparation": {
      "autoDeductCharges": false,
      "spontaneousPrepared": false
    },
    "sr": false,
    "shortDescription": "<p>You summon a black pudding (<i>Bestiary</i> 35) that immediately attacks creatures near it. You have no control over the creature, and it may attack you if there are no more obvious opponents. The black pudding is treated as a summoned creature and has the extraplanar subtype. The black pudding's split ability works normally, but all puddings derived from the summoned one disappear when the spell ends.</p>"
  },
  "effects": [],
  "folder": null,
  "sort": 0,
  "permission": {
    "default": 0
  },
  "flags": {}
}